tinyml/__init__.py
tinyml/autograd/__init__.py
tinyml/core/__init__.py
tinyml/core/backend.py
tinyml/core/parameter.py
tinyml/dataloaders/__init__.py
tinyml/dataloaders/cifar.py
tinyml/dataloaders/imagenet.py
tinyml/dataloaders/mnist.py
tinyml/functional/__init__.py
tinyml/functional/polynomial_regression.py
tinyml/layers/__init__.py
tinyml/layers/base.py
tinyml/layers/conv1d.py
tinyml/layers/convolution.py
tinyml/layers/deconvolution.py
tinyml/layers/dropout.py
tinyml/layers/flatten.py
tinyml/layers/linear.py
tinyml/layers/pooling.py
tinyml/layers/relu.py
tinyml/layers/softmax.py
tinyml/layers/unpooling.py
tinyml/learner/__init__.py
tinyml/learner/callbacks.py
tinyml/learner/hooks.py
tinyml/learner/learner.py
tinyml/losses/__init__.py
tinyml/losses/cross_entropy.py
tinyml/losses/mse.py
tinyml/net/__init__.py
tinyml/net/base.py
tinyml/net/sequential.py
tinyml/optims/__init__.py
tinyml/optims/sgd.py
tinyml/utilities/__init__.py
tinyml/utilities/checker.py
tinyml/utilities/logger.py
tinyml/utilities/persist.py
tinyml/utilities/visualizer.py
tinyml-0.0.6.dist-info/METADATA
tinyml-0.0.6.dist-info/WHEEL
tinyml-0.0.6.dist-info/top_level.txt
tinyml-0.0.6.dist-info/RECORD
