Metadata-Version: 2.1
Name: tinyml
Version: 0.0.6
Summary: A Pure Python Machine Learning Library
Home-page: https://github.com/autoai-org/tinyml
Author: Xiaozhe Yao
Author-email: askxzyao@gmail.com
License: UNKNOWN
Platform: UNKNOWN
Classifier: Programming Language :: Python :: 3
Classifier: License :: OSI Approved :: MIT License
Classifier: Operating System :: OS Independent
Requires-Python: >=3.6
